{"2024-10-09 15:12:51":{"userName":"User33","password":"Lösen33"},"2024-10-09 15:13:10":{"userName":"Ollie94","password":"Lösen94"},"2024-10-09 15:12:21":{"userName":"User11","password":"Lösen11"},"2024-10-09 15:13:03":{"userName":"User55","password":"Lösen55"},"2024-10-09 15:12:34":{"userName":"User22","password":"Lösen22"},"2024-10-09 15:12:56":{"userName":"User","password":"44"},"2024-10-09 15:13:24":{"userName":"Helena89","password":"Lösen89"},"2024-10-09 15:13:16":{"userName":"David88","password":"Lösen88"}}